[
    {
        "timestamp":  "2025-12-14T15:58:45.396Z",
        "level":  "INFO",
        "message":  "=== Starting AOP Web (Production Mode) ===",
        "script":  "Start_AOP_Web.ps1",
        "metadata":  {

                     }
    },
    {
        "timestamp":  "2025-12-14T15:58:45.443Z",
        "level":  "INFO",
        "message":  "Cleaning old logs...",
        "script":  "Start_AOP_Web.ps1",
        "metadata":  {

                     }
    },
    {
        "timestamp":  "2025-12-14T15:58:45.584Z",
        "level":  "INFO",
        "message":  "Setting up backend...",
        "script":  "Start_AOP_Web.ps1",
        "metadata":  {

                     }
    },
    {
        "timestamp":  "2025-12-14T15:58:45.600Z",
        "level":  "INFO",
        "message":  "Using virtual environment",
        "script":  "Start_AOP_Web.ps1",
        "metadata":  {

                     }
    },
    {
        "timestamp":  "2025-12-14T15:58:45.693Z",
        "level":  "INFO",
        "message":  "Python version: Python 3.12.9",
        "script":  "Start_AOP_Web.ps1",
        "metadata":  {

                     }
    },
    {
        "timestamp":  "2025-12-14T15:58:45.709Z",
        "level":  "INFO",
        "message":  "Checking port 5000...",
        "script":  "Start_AOP_Web.ps1",
        "metadata":  {

                     }
    },
    {
        "timestamp":  "2025-12-14T15:58:47.240Z",
        "level":  "WARN",
        "message":  "Found process using port 5000 : python (PID: 3572)",
        "script":  "Start_AOP_Web.ps1",
        "metadata":  {

                     }
    },
    {
        "timestamp":  "2025-12-14T15:58:47.271Z",
        "level":  "INFO",
        "message":  "Stopped process PID: 3572 on port 5000",
        "script":  "Start_AOP_Web.ps1",
        "metadata":  {

                     }
    },
    {
        "timestamp":  "2025-12-14T15:58:47.787Z",
        "level":  "INFO",
        "message":  "Port 5000 is now available",
        "script":  "Start_AOP_Web.ps1",
        "metadata":  {

                     }
    },
    {
        "timestamp":  "2025-12-14T15:58:47.787Z",
        "level":  "INFO",
        "message":  "Starting backend server (Port 5000)...",
        "script":  "Start_AOP_Web.ps1",
        "metadata":  {

                     }
    },
    {
        "timestamp":  "2025-12-14T15:58:47.912Z",
        "level":  "INFO",
        "message":  "Backend PID: 4892",
        "script":  "Start_AOP_Web.ps1",
        "metadata":  {
                         "port":  5000,
                         "pid":  4892,
                         "service":  "backend",
                         "python":  "C:\\AOP_Tools\\AOP_Web\\backend\\.venv\\Scripts\\python.exe"
                     }
    },
    {
        "timestamp":  "2025-12-14T15:58:47.928Z",
        "level":  "INFO",
        "message":  "Verifying backend startup...",
        "script":  "Start_AOP_Web.ps1",
        "metadata":  {

                     }
    },
    {
        "timestamp":  "2025-12-14T15:58:53.037Z",
        "level":  "INFO",
        "message":  "Backend is listening on port 5000",
        "script":  "Start_AOP_Web.ps1",
        "metadata":  {

                     }
    },
    {
        "timestamp":  "2025-12-14T15:58:53.037Z",
        "level":  "INFO",
        "message":  "Backend started successfully",
        "script":  "Start_AOP_Web.ps1",
        "metadata":  {

                     }
    },
    {
        "timestamp":  "2025-12-14T15:58:53.053Z",
        "level":  "INFO",
        "message":  "Setting up frontend...",
        "script":  "Start_AOP_Web.ps1",
        "metadata":  {

                     }
    },
    {
        "timestamp":  "2025-12-14T15:58:53.849Z",
        "level":  "INFO",
        "message":  "Node v20.19.4 | npm 10.8.2",
        "script":  "Start_AOP_Web.ps1",
        "metadata":  {

                     }
    },
    {
        "timestamp":  "2025-12-14T15:58:53.849Z",
        "level":  "INFO",
        "message":  "Checking port 3000...",
        "script":  "Start_AOP_Web.ps1",
        "metadata":  {

                     }
    },
    {
        "timestamp":  "2025-12-14T15:58:53.928Z",
        "level":  "WARN",
        "message":  "Found process using port 3000 : node (PID: 6808)",
        "script":  "Start_AOP_Web.ps1",
        "metadata":  {

                     }
    },
    {
        "timestamp":  "2025-12-14T15:58:53.943Z",
        "level":  "INFO",
        "message":  "Stopped process PID: 6808 on port 3000",
        "script":  "Start_AOP_Web.ps1",
        "metadata":  {

                     }
    },
    {
        "timestamp":  "2025-12-14T15:58:54.459Z",
        "level":  "INFO",
        "message":  "Port 3000 is now available",
        "script":  "Start_AOP_Web.ps1",
        "metadata":  {

                     }
    },
    {
        "timestamp":  "2025-12-14T15:58:54.459Z",
        "level":  "INFO",
        "message":  "Starting frontend server (Port 3000)...",
        "script":  "Start_AOP_Web.ps1",
        "metadata":  {

                     }
    },
    {
        "timestamp":  "2025-12-14T15:58:54.474Z",
        "level":  "INFO",
        "message":  "Building frontend...",
        "script":  "Start_AOP_Web.ps1",
        "metadata":  {

                     }
    },
    {
        "timestamp":  "2025-12-14T15:59:17.287Z",
        "level":  "INFO",
        "message":  "Starting frontend in production mode...",
        "script":  "Start_AOP_Web.ps1",
        "metadata":  {

                     }
    },
    {
        "timestamp":  "2025-12-14T15:59:17.350Z",
        "level":  "INFO",
        "message":  "Frontend PID: 7064",
        "script":  "Start_AOP_Web.ps1",
        "metadata":  {
                         "port":  3000,
                         "pid":  7064,
                         "service":  "frontend",
                         "mode":  "Production"
                     }
    },
    {
        "timestamp":  "2025-12-14T15:59:22.350Z",
        "level":  "INFO",
        "message":  "=== Startup Complete ===",
        "script":  "Start_AOP_Web.ps1",
        "metadata":  {

                     }
    },
    {
        "timestamp":  "2025-12-14T15:59:22.350Z",
        "level":  "INFO",
        "message":  "Backend:  http://localhost:5000",
        "script":  "Start_AOP_Web.ps1",
        "metadata":  {

                     }
    },
    {
        "timestamp":  "2025-12-14T15:59:22.365Z",
        "level":  "INFO",
        "message":  "Frontend: http://localhost:3000",
        "script":  "Start_AOP_Web.ps1",
        "metadata":  {

                     }
    },
    {
        "timestamp":  "2025-12-14T15:59:22.365Z",
        "level":  "INFO",
        "message":  "Log file: C:\\AOP_Tools\\AOP_Web\\logs\\startup_20251214_155845.log",
        "script":  "Start_AOP_Web.ps1",
        "metadata":  {

                     }
    }
]
